{
    "left": {
        "left": {
            "left": {
                "left": {
                    "left": null,
                    "node": {
                        "distance_from_earth": 91.7877987534291,
                        "sector_code": "91LDB",
                        "x": -90,
                        "y": -10,
                        "z": -15
                    },
                    "right": null
                },
                "node": {
                    "distance_from_earth": 129.52991932368366,
                    "sector_code": "129LDB",
                    "x": -89,
                    "y": -91,
                    "z": -24
                },
                "right": null
            },
            "node": {
                "distance_from_earth": 103.34892355511015,
                "sector_code": "103LDB",
                "x": -84,
                "y": -51,
                "z": -32
            },
            "right": {
                "left": {
                    "left": {
                        "left": null,
                        "node": {
                            "distance_from_earth": 107.70793842609746,
                            "sector_code": "107LDB",
                            "x": -74,
                            "y": -77,
                            "z": -14
                        },
                        "right": null
                    },
                    "node": {
                        "distance_from_earth": 101.12863096077193,
                        "sector_code": "101LDF",
                        "x": -71,
                        "y": -31,
                        "z": 65
                    },
                    "right": {
                        "left": null,
                        "node": {
                            "distance_from_earth": 111.57508682497182,
                            "sector_code": "111LUF",
                            "x": -62,
                            "y": 69,
                            "z": 62
                        },
                        "right": null
                    }
                },
                "node": {
                    "distance_from_earth": 77.38216848861241,
                    "sector_code": "77LDB",
                    "x": -32,
                    "y": -8,
                    "z": -70
                },
                "right": {
                    "left": null,
                    "node": {
                        "distance_from_earth": 114.86513831445988,
                        "sector_code": "114LUF",
                        "x": -28,
                        "y": 67,
                        "z": 89
                    },
                    "right": null
                }
            }
        },
        "node": {
            "distance_from_earth": 99.38812806366765,
            "sector_code": "99LDB",
            "x": -23,
            "y": -18,
            "z": -95
        },
        "right": {
            "left": null,
            "node": {
                "distance_from_earth": 120.75595223424807,
                "sector_code": "120LUF",
                "x": -2,
                "y": 77,
                "z": 93
            },
            "right": null
        }
    },
    "node": {
        "distance_from_earth": 0.0,
        "sector_code": "0SSS",
        "x": 0,
        "y": 0,
        "z": 0
    },
    "right": {
        "left": {
            "left": null,
            "node": {
                "distance_from_earth": 88.82004278314665,
                "sector_code": "88RDB",
                "x": 8,
                "y": -9,
                "z": -88
            },
            "right": {
                "left": null,
                "node": {
                    "distance_from_earth": 26.92582403567252,
                    "sector_code": "26RUB",
                    "x": 8,
                    "y": 25,
                    "z": -6
                },
                "right": null
            }
        },
        "node": {
            "distance_from_earth": 110.41738993473808,
            "sector_code": "110RDB",
            "x": 32,
            "y": -92,
            "z": -52
        },
        "right": {
            "left": {
                "left": null,
                "node": {
                    "distance_from_earth": 115.15207336387826,
                    "sector_code": "115RDF",
                    "x": 50,
                    "y": -98,
                    "z": 34
                },
                "right": null
            },
            "node": {
                "distance_from_earth": 86.16843969807043,
                "sector_code": "86RDF",
                "x": 50,
                "y": -53,
                "z": 46
            },
            "right": {
                "left": {
                    "left": {
                        "left": {
                            "left": null,
                            "node": {
                                "distance_from_earth": 130.12301871690497,
                                "sector_code": "130RDB",
                                "x": 52,
                                "y": -98,
                                "z": -68
                            },
                            "right": {
                                "left": null,
                                "node": {
                                    "distance_from_earth": 131.40776232780163,
                                    "sector_code": "131RUB",
                                    "x": 64,
                                    "y": 86,
                                    "z": -76
                                },
                                "right": null
                            }
                        },
                        "node": {
                            "distance_from_earth": 84.0535543567314,
                            "sector_code": "84RUF",
                            "x": 70,
                            "y": 7,
                            "z": 46
                        },
                        "right": null
                    },
                    "node": {
                        "distance_from_earth": 121.69223475637219,
                        "sector_code": "121RDB",
                        "x": 78,
                        "y": -25,
                        "z": -90
                    },
                    "right": null
                },
                "node": {
                    "distance_from_earth": 84.76437931112338,
                    "sector_code": "84RDB",
                    "x": 80,
                    "y": -23,
                    "z": -16
                },
                "right": {
                    "left": null,
                    "node": {
                        "distance_from_earth": 109.4988584415381,
                        "sector_code": "109RUB",
                        "x": 89,
                        "y": 15,
                        "z": -62
                    },
                    "right": null
                }
            }
        }
    }
}